README.md
setup.py
pyopenmx/__init__.py
pyopenmx/constant.py
pyopenmx.egg-info/PKG-INFO
pyopenmx.egg-info/SOURCES.txt
pyopenmx.egg-info/dependency_links.txt
pyopenmx.egg-info/not-zip-safe
pyopenmx.egg-info/requires.txt
pyopenmx.egg-info/top_level.txt