Metadata-Version: 2.1
Name: pyopenmx
Version: 0.0.1
Summary: pyopenmx
Home-page: https://gitee.com/alkemie_gjwang/pyopenmx
Author: Guanjie Wang
Author-email: gjwang@buaa.edu.cn
License: MIT
Platform: UNKNOWN
